ndlinear/__init__.py
ndlinear/ndlinear.py
ndlinear-1.0.0.dist-info/licenses/LICENSE
ndlinear-1.0.0.dist-info/METADATA
ndlinear-1.0.0.dist-info/WHEEL
ndlinear-1.0.0.dist-info/top_level.txt
ndlinear-1.0.0.dist-info/RECORD
