Metadata-Version: 2.4
Name: ndlinear
Version: 1.0.0
Summary: NdLinear: A multi-dimensional linear transformation layer.
Home-page: https://github.com/ensemble-core/NdLinear
Author: Alex Reneau, Jerry Yao-Chieh Hu, Zhongfang Zhuang, Ting-Chun Liu
Classifier: Programming Language :: Python :: 3
Classifier: License :: OSI Approved :: Apache Software License
Classifier: Operating System :: OS Independent
Requires-Python: >=3.9
License-File: LICENSE
Requires-Dist: torch>=2.3.0
Requires-Dist: numpy>=1.24.3
Dynamic: author
Dynamic: classifier
Dynamic: description
Dynamic: description-content-type
Dynamic: home-page
Dynamic: license-file
Dynamic: requires-dist
Dynamic: requires-python
Dynamic: summary
